[
  {
    "streetName": "Veterans Road",
    "coordinates": [
      {
        "lat": 14.5081511,
        "lng": 121.0387173
      },
      {
        "lat": 14.5080012,
        "lng": 121.0387898
      },
      {
        "lat": 14.5075396,
        "lng": 121.0390276
      },
      {
        "lat": 14.5070733,
        "lng": 121.0392821
      },
      {
        "lat": 14.5068999,
        "lng": 121.0393757
      },
      {
        "lat": 14.5068632,
        "lng": 121.0394018
      },
      {
        "lat": 14.5068216,
        "lng": 121.0394387
      },
      {
        "lat": 14.5067963,
        "lng": 121.0395309
      },
      {
        "lat": 14.5060958,
        "lng": 121.0400027
      },
      {
        "lat": 14.5060541,
        "lng": 121.040007
      },
      {
        "lat": 14.5060034,
        "lng": 121.0399939
      },
      {
        "lat": 14.5059727,
        "lng": 121.0399763
      },
      {
        "lat": 14.5082791,
        "lng": 121.0390402
      },
      {
        "lat": 14.5075835,
        "lng": 121.0394121
      },
      {
        "lat": 14.5074941,
        "lng": 121.0394842
      },
      {
        "lat": 14.5074323,
        "lng": 121.0395534
      },
      {
        "lat": 14.5073646,
        "lng": 121.0396622
      },
      {
        "lat": 14.5073203,
        "lng": 121.0397785
      },
      {
        "lat": 14.5073,
        "lng": 121.0398864
      },
      {
        "lat": 14.5072976,
        "lng": 121.039995
      },
      {
        "lat": 14.5073121,
        "lng": 121.0400994
      },
      {
        "lat": 14.507357,
        "lng": 121.040233
      },
      {
        "lat": 14.5076022,
        "lng": 121.0407107
      },
      {
        "lat": 14.5077314,
        "lng": 121.0409695
      },
      {
        "lat": 14.508035,
        "lng": 121.041562
      },
      {
        "lat": 14.5086303,
        "lng": 121.0427064
      },
      {
        "lat": 14.5086586,
        "lng": 121.0427615
      },
      {
        "lat": 14.5090301,
        "lng": 121.043485
      },
      {
        "lat": 14.5090821,
        "lng": 121.043588
      },
      {
        "lat": 14.5094189,
        "lng": 121.0442546
      },
      {
        "lat": 14.5094887,
        "lng": 121.0443887
      },
      {
        "lat": 14.5097553,
        "lng": 121.044901
      },
      {
        "lat": 14.5099816,
        "lng": 121.0453671
      },
      {
        "lat": 14.5102882,
        "lng": 121.0459569
      },
      {
        "lat": 14.510457,
        "lng": 121.0462636
      },
      {
        "lat": 14.5104713,
        "lng": 121.0462935
      },
      {
        "lat": 14.5104859,
        "lng": 121.0463119
      },
      {
        "lat": 14.510541,
        "lng": 121.046381
      },
      {
        "lat": 14.5106218,
        "lng": 121.0464763
      },
      {
        "lat": 14.5106941,
        "lng": 121.0465675
      },
      {
        "lat": 14.5105147,
        "lng": 121.0466388
      },
      {
        "lat": 14.510585,
        "lng": 121.0466079
      },
      {
        "lat": 14.5106323,
        "lng": 121.0465904
      },
      {
        "lat": 14.5106941,
        "lng": 121.0465675
      },
      {
        "lat": 14.5107624,
        "lng": 121.0465952
      },
      {
        "lat": 14.5108899,
        "lng": 121.0466514
      },
      {
        "lat": 14.5111528,
        "lng": 121.0467545
      },
      {
        "lat": 14.5114327,
        "lng": 121.0468047
      },
      {
        "lat": 14.5117602,
        "lng": 121.0468159
      },
      {
        "lat": 14.5118337,
        "lng": 121.0468158
      },
      {
        "lat": 14.5121131,
        "lng": 121.0468204
      },
      {
        "lat": 14.5124343,
        "lng": 121.0468318
      },
      {
        "lat": 14.5127965,
        "lng": 121.0468419
      },
      {
        "lat": 14.5128237,
        "lng": 121.0468438
      },
      {
        "lat": 14.5136569,
        "lng": 121.0468683
      },
      {
        "lat": 14.5137852,
        "lng": 121.0469363
      },
      {
        "lat": 14.5138826,
        "lng": 121.0470149
      },
      {
        "lat": 14.5139801,
        "lng": 121.0471431
      },
      {
        "lat": 14.5141236,
        "lng": 121.0474248
      },
      {
        "lat": 14.5141879,
        "lng": 121.0475512
      },
      {
        "lat": 14.514342,
        "lng": 121.0478484
      },
      {
        "lat": 14.5147336,
        "lng": 121.0486048
      },
      {
        "lat": 14.5149513,
        "lng": 121.0490438
      },
      {
        "lat": 14.515142,
        "lng": 121.0494128
      },
      {
        "lat": 14.5156118,
        "lng": 121.0503031
      },
      {
        "lat": 14.5156989,
        "lng": 121.0504256
      },
      {
        "lat": 14.5157729,
        "lng": 121.0505383
      },
      {
        "lat": 14.5159317,
        "lng": 121.0508328
      },
      {
        "lat": 14.5159657,
        "lng": 121.0508958
      },
      {
        "lat": 14.516041,
        "lng": 121.0509772
      },
      {
        "lat": 14.5059727,
        "lng": 121.0399763
      },
      {
        "lat": 14.5059102,
        "lng": 121.0398785
      },
      {
        "lat": 14.5058633,
        "lng": 121.0398087
      },
      {
        "lat": 14.5057804,
        "lng": 121.0396852
      },
      {
        "lat": 14.5056776,
        "lng": 121.0395312
      },
      {
        "lat": 14.5094788,
        "lng": 121.0380527
      },
      {
        "lat": 14.5093957,
        "lng": 121.0380905
      },
      {
        "lat": 14.5093848,
        "lng": 121.038096
      },
      {
        "lat": 14.5091563,
        "lng": 121.0382115
      },
      {
        "lat": 14.5091439,
        "lng": 121.0382177
      },
      {
        "lat": 14.5091333,
        "lng": 121.0382229
      },
      {
        "lat": 14.508737,
        "lng": 121.0384228
      },
      {
        "lat": 14.5081511,
        "lng": 121.0387173
      },
      {
        "lat": 14.5056014,
        "lng": 121.0396012
      },
      {
        "lat": 14.5057031,
        "lng": 121.0397398
      },
      {
        "lat": 14.5057915,
        "lng": 121.0398498
      },
      {
        "lat": 14.5058109,
        "lng": 121.0398681
      },
      {
        "lat": 14.5058803,
        "lng": 121.0399336
      },
      {
        "lat": 14.5059727,
        "lng": 121.0399763
      },
      {
        "lat": 14.5067963,
        "lng": 121.0395309
      },
      {
        "lat": 14.5067074,
        "lng": 121.0396197
      },
      {
        "lat": 14.5066279,
        "lng": 121.0396988
      },
      {
        "lat": 14.5060958,
        "lng": 121.0400027
      }
    ],
    "color": "#FFFF00"
  },
  {
    "streetName": "Duhat Street",
    "coordinates": [
      {
        "lat": 14.5099039,
        "lng": 121.0387367
      },
      {
        "lat": 14.5100923,
        "lng": 121.0387034
      },
      {
        "lat": 14.510456,
        "lng": 121.0385421
      },
      {
        "lat": 14.5106359,
        "lng": 121.0384303
      },
      {
        "lat": 14.5107202,
        "lng": 121.0383698
      },
      {
        "lat": 14.5108347,
        "lng": 121.0382626
      },
      {
        "lat": 14.5109139,
        "lng": 121.038151
      }
    ],
    "color": "#FFFF00"
  },
  {
    "streetName": "Dalandan Street",
    "coordinates": [
      {
        "lat": 14.5119887,
        "lng": 121.037808
      },
      {
        "lat": 14.5119127,
        "lng": 121.0376312
      },
      {
        "lat": 14.5118573,
        "lng": 121.0374798
      },
      {
        "lat": 14.5117836,
        "lng": 121.0372509
      },
      {
        "lat": 14.511692,
        "lng": 121.0368817
      },
      {
        "lat": 14.5115911,
        "lng": 121.0365967
      },
      {
        "lat": 14.5115589,
        "lng": 121.0365135
      },
      {
        "lat": 14.5114588,
        "lng": 121.0362638
      },
      {
        "lat": 14.5113332,
        "lng": 121.0359644
      }
    ],
    "color": "#FFFF00"
  },
  {
    "streetName": "Yengco Street",
    "coordinates": [
      {
        "lat": 14.5255095,
        "lng": 121.0394111
      },
      {
        "lat": 14.5257216,
        "lng": 121.0393009
      },
      {
        "lat": 14.5262389,
        "lng": 121.0392873
      },
      {
        "lat": 14.52637,
        "lng": 121.0392866
      },
      {
        "lat": 14.5264189,
        "lng": 121.0392495
      }
    ],
    "color": "#FFFF00"
  },
  {
    "streetName": "Avocado",
    "coordinates": [
      {
        "lat": 14.5250234,
        "lng": 121.0323065
      },
      {
        "lat": 14.5255342,
        "lng": 121.0332789
      }
    ],
    "color": "#FFFF00"
  },
  {
    "streetName": "Bayani Road",
    "coordinates": [
      {
        "lat": 14.5339107,
        "lng": 121.0409028
      },
      {
        "lat": 14.5328432,
        "lng": 121.0409752
      },
      {
        "lat": 14.5321739,
        "lng": 121.0410231
      },
      {
        "lat": 14.5339126,
        "lng": 121.0409753
      },
      {
        "lat": 14.534415,
        "lng": 121.0409551
      },
      {
        "lat": 14.534565,
        "lng": 121.0409422
      },
      {
        "lat": 14.5347111,
        "lng": 121.040936
      },
      {
        "lat": 14.5347647,
        "lng": 121.040935
      },
      {
        "lat": 14.5347691,
        "lng": 121.0408659
      },
      {
        "lat": 14.5347146,
        "lng": 121.0408647
      },
      {
        "lat": 14.534584,
        "lng": 121.0408684
      },
      {
        "lat": 14.5304332,
        "lng": 121.0412613
      },
      {
        "lat": 14.5306962,
        "lng": 121.0412153
      },
      {
        "lat": 14.5308416,
        "lng": 121.0411936
      },
      {
        "lat": 14.5313147,
        "lng": 121.0411599
      },
      {
        "lat": 14.5321795,
        "lng": 121.0410983
      },
      {
        "lat": 14.5328387,
        "lng": 121.041049
      },
      {
        "lat": 14.5339126,
        "lng": 121.0409753
      },
      {
        "lat": 14.5196719,
        "lng": 121.0472881
      },
      {
        "lat": 14.5195391,
        "lng": 121.0474492
      },
      {
        "lat": 14.5194194,
        "lng": 121.0476215
      },
      {
        "lat": 14.5193185,
        "lng": 121.0478154
      },
      {
        "lat": 14.5192554,
        "lng": 121.0479687
      },
      {
        "lat": 14.5192092,
        "lng": 121.0481322
      },
      {
        "lat": 14.5191828,
        "lng": 121.0483037
      },
      {
        "lat": 14.52179,
        "lng": 121.0466834
      },
      {
        "lat": 14.5206807,
        "lng": 121.0468043
      },
      {
        "lat": 14.5204879,
        "lng": 121.0468418
      },
      {
        "lat": 14.5203139,
        "lng": 121.0468936
      },
      {
        "lat": 14.5201369,
        "lng": 121.0469575
      },
      {
        "lat": 14.5199628,
        "lng": 121.0470587
      },
      {
        "lat": 14.5198124,
        "lng": 121.0471726
      },
      {
        "lat": 14.5196719,
        "lng": 121.0472881
      },
      {
        "lat": 14.5253332,
        "lng": 121.0435371
      },
      {
        "lat": 14.5252937,
        "lng": 121.0435666
      },
      {
        "lat": 14.5252489,
        "lng": 121.0436063
      },
      {
        "lat": 14.5254286,
        "lng": 121.0434755
      },
      {
        "lat": 14.5253332,
        "lng": 121.0435371
      },
      {
        "lat": 14.5252489,
        "lng": 121.0436063
      },
      {
        "lat": 14.5252158,
        "lng": 121.0436404
      },
      {
        "lat": 14.5251847,
        "lng": 121.0436806
      },
      {
        "lat": 14.5251665,
        "lng": 121.0437093
      },
      {
        "lat": 14.5251406,
        "lng": 121.0437718
      },
      {
        "lat": 14.5251054,
        "lng": 121.043893
      },
      {
        "lat": 14.5250607,
        "lng": 121.0440816
      },
      {
        "lat": 14.5249603,
        "lng": 121.0444701
      },
      {
        "lat": 14.5246535,
        "lng": 121.0457427
      },
      {
        "lat": 14.5245929,
        "lng": 121.0459067
      },
      {
        "lat": 14.5245227,
        "lng": 121.046038
      },
      {
        "lat": 14.5244416,
        "lng": 121.0461371
      },
      {
        "lat": 14.5243224,
        "lng": 121.046253
      },
      {
        "lat": 14.5241528,
        "lng": 121.0463583
      },
      {
        "lat": 14.5239932,
        "lng": 121.0464248
      },
      {
        "lat": 14.523873,
        "lng": 121.0464559
      },
      {
        "lat": 14.523708,
        "lng": 121.0464791
      },
      {
        "lat": 14.5226553,
        "lng": 121.0465875
      },
      {
        "lat": 14.52179,
        "lng": 121.0466834
      },
      {
        "lat": 14.5191828,
        "lng": 121.0483037
      },
      {
        "lat": 14.5191715,
        "lng": 121.048515
      },
      {
        "lat": 14.5191813,
        "lng": 121.0487331
      },
      {
        "lat": 14.5191947,
        "lng": 121.0488878
      },
      {
        "lat": 14.5192252,
        "lng": 121.049106
      },
      {
        "lat": 14.519236,
        "lng": 121.0491833
      },
      {
        "lat": 14.5192828,
        "lng": 121.0495023
      },
      {
        "lat": 14.5192911,
        "lng": 121.0496343
      },
      {
        "lat": 14.5192898,
        "lng": 121.0497779
      },
      {
        "lat": 14.5192688,
        "lng": 121.0499138
      },
      {
        "lat": 14.5192276,
        "lng": 121.0500366
      },
      {
        "lat": 14.5191609,
        "lng": 121.0501696
      },
      {
        "lat": 14.5190845,
        "lng": 121.0502658
      },
      {
        "lat": 14.518972,
        "lng": 121.0503614
      },
      {
        "lat": 14.5188376,
        "lng": 121.0504481
      },
      {
        "lat": 14.5187021,
        "lng": 121.0505144
      },
      {
        "lat": 14.5183252,
        "lng": 121.0506693
      },
      {
        "lat": 14.5179591,
        "lng": 121.0507934
      },
      {
        "lat": 14.5178595,
        "lng": 121.0508281
      },
      {
        "lat": 14.5178259,
        "lng": 121.0508385
      },
      {
        "lat": 14.5176948,
        "lng": 121.0508839
      },
      {
        "lat": 14.5267794,
        "lng": 121.0427366
      },
      {
        "lat": 14.5269061,
        "lng": 121.0426784
      },
      {
        "lat": 14.5282079,
        "lng": 121.0421534
      },
      {
        "lat": 14.5187021,
        "lng": 121.0505144
      },
      {
        "lat": 14.5185032,
        "lng": 121.0505982
      },
      {
        "lat": 14.5183252,
        "lng": 121.0506693
      },
      {
        "lat": 14.5304329,
        "lng": 121.0411897
      },
      {
        "lat": 14.5301854,
        "lng": 121.0412572
      },
      {
        "lat": 14.5300462,
        "lng": 121.0413053
      },
      {
        "lat": 14.5296831,
        "lng": 121.041445
      },
      {
        "lat": 14.5290239,
        "lng": 121.0417228
      },
      {
        "lat": 14.5281794,
        "lng": 121.0420788
      },
      {
        "lat": 14.5250607,
        "lng": 121.0440816
      },
      {
        "lat": 14.5249603,
        "lng": 121.0444701
      },
      {
        "lat": 14.5321739,
        "lng": 121.0410231
      },
      {
        "lat": 14.5313108,
        "lng": 121.0410897
      },
      {
        "lat": 14.5308966,
        "lng": 121.0411217
      },
      {
        "lat": 14.5304329,
        "lng": 121.0411897
      },
      {
        "lat": 14.534415,
        "lng": 121.0409551
      },
      {
        "lat": 14.534565,
        "lng": 121.0409422
      },
      {
        "lat": 14.5254761,
        "lng": 121.0435366
      },
      {
        "lat": 14.5257355,
        "lng": 121.04336
      },
      {
        "lat": 14.5257792,
        "lng": 121.0433298
      },
      {
        "lat": 14.5261799,
        "lng": 121.0430779
      },
      {
        "lat": 14.5264221,
        "lng": 121.0429277
      },
      {
        "lat": 14.5267794,
        "lng": 121.0427366
      },
      {
        "lat": 14.5281794,
        "lng": 121.0420788
      },
      {
        "lat": 14.5268808,
        "lng": 121.0426097
      },
      {
        "lat": 14.5267505,
        "lng": 121.0426687
      },
      {
        "lat": 14.526677,
        "lng": 121.0427073
      },
      {
        "lat": 14.5263813,
        "lng": 121.0428757
      },
      {
        "lat": 14.5263417,
        "lng": 121.0428998
      },
      {
        "lat": 14.526219,
        "lng": 121.0429745
      },
      {
        "lat": 14.5260533,
        "lng": 121.0430755
      },
      {
        "lat": 14.5257233,
        "lng": 121.0432903
      },
      {
        "lat": 14.5257011,
        "lng": 121.0433042
      },
      {
        "lat": 14.5255097,
        "lng": 121.0434243
      },
      {
        "lat": 14.5254286,
        "lng": 121.0434755
      },
      {
        "lat": 14.5282079,
        "lng": 121.0421534
      },
      {
        "lat": 14.5290537,
        "lng": 121.0417978
      },
      {
        "lat": 14.5297119,
        "lng": 121.041521
      },
      {
        "lat": 14.5301948,
        "lng": 121.0413277
      },
      {
        "lat": 14.5304332,
        "lng": 121.0412613
      },
      {
        "lat": 14.534584,
        "lng": 121.0408684
      },
      {
        "lat": 14.5339107,
        "lng": 121.0409028
      }
    ],
    "color": "#FFFF00"
  },
  {
    "streetName": "C. Duque Street",
    "coordinates": [
      {
        "lat": 14.5205024,
        "lng": 121.0366605
      },
      {
        "lat": 14.5206269,
        "lng": 121.0365715
      },
      {
        "lat": 14.5206997,
        "lng": 121.0364941
      },
      {
        "lat": 14.5207801,
        "lng": 121.0364133
      },
      {
        "lat": 14.5208221,
        "lng": 121.0363435
      },
      {
        "lat": 14.5208885,
        "lng": 121.0362458
      },
      {
        "lat": 14.521038,
        "lng": 121.0359282
      },
      {
        "lat": 14.5211554,
        "lng": 121.0357269
      },
      {
        "lat": 14.521186,
        "lng": 121.0356729
      },
      {
        "lat": 14.5213335,
        "lng": 121.035534
      },
      {
        "lat": 14.5215456,
        "lng": 121.0353623
      },
      {
        "lat": 14.5217011,
        "lng": 121.0352763
      }
    ],
    "color": "#FFFF00"
  },
  {
    "streetName": "Rosal",
    "coordinates": [
      {
        "lat": 14.5159025,
        "lng": 121.0309081
      },
      {
        "lat": 14.5165436,
        "lng": 121.0322124
      }
    ],
    "color": "#FFFF00"
  },
  {
    "streetName": "Nabua Street",
    "coordinates": [
      {
        "lat": 14.514279,
        "lng": 121.0394154
      },
      {
        "lat": 14.514216,
        "lng": 121.0394416
      },
      {
        "lat": 14.5139831,
        "lng": 121.0395412
      },
      {
        "lat": 14.5136909,
        "lng": 121.0396526
      }
    ],
    "color": "#FFFF00"
  },
  {
    "streetName": "Gumamela",
    "coordinates": [
      {
        "lat": 14.5195483,
        "lng": 121.0362977
      },
      {
        "lat": 14.5189785,
        "lng": 121.0351394
      },
      {
        "lat": 14.518458,
        "lng": 121.0340814
      }
    ],
    "color": "#FFFF00"
  },
  {
    "streetName": "Bougainvillea",
    "coordinates": [
      {
        "lat": 14.5180301,
        "lng": 121.0331561
      },
      {
        "lat": 14.5177388,
        "lng": 121.033308
      },
      {
        "lat": 14.5174612,
        "lng": 121.0334528
      },
      {
        "lat": 14.5168252,
        "lng": 121.0337844
      }
    ],
    "color": "#FFFF00"
  },
  {
    "streetName": "Waling-waling",
    "coordinates": [
      {
        "lat": 14.5187811,
        "lng": 121.0353855
      },
      {
        "lat": 14.5185789,
        "lng": 121.0354983
      },
      {
        "lat": 14.5183778,
        "lng": 121.0356105
      },
      {
        "lat": 14.5179905,
        "lng": 121.0358284
      }
    ],
    "color": "#FFFF00"
  },
  {
    "streetName": "Orchid",
    "coordinates": [
      {
        "lat": 14.5168573,
        "lng": 121.0303956
      },
      {
        "lat": 14.5174994,
        "lng": 121.0317242
      },
      {
        "lat": 14.5179575,
        "lng": 121.0326554
      }
    ],
    "color": "#FFFF00"
  },
  {
    "streetName": "Palo Maria Street",
    "coordinates": [
      {
        "lat": 14.5103518,
        "lng": 121.0382988
      },
      {
        "lat": 14.5097508,
        "lng": 121.0386191
      }
    ],
    "color": "#FFFF00"
  },
  {
    "streetName": "East Union Drive",
    "coordinates": [
      {
        "lat": 14.5041367,
        "lng": 121.0483302
      },
      {
        "lat": 14.5053435,
        "lng": 121.0476663
      },
      {
        "lat": 14.5053565,
        "lng": 121.0476592
      },
      {
        "lat": 14.5061587,
        "lng": 121.0472169
      },
      {
        "lat": 14.5063215,
        "lng": 121.0471271
      },
      {
        "lat": 14.506547,
        "lng": 121.047
      },
      {
        "lat": 14.5069448,
        "lng": 121.0467838
      },
      {
        "lat": 14.5070015,
        "lng": 121.0467526
      },
      {
        "lat": 14.5070015,
        "lng": 121.0467526
      },
      {
        "lat": 14.5070808,
        "lng": 121.046714
      },
      {
        "lat": 14.5070808,
        "lng": 121.046714
      },
      {
        "lat": 14.5071932,
        "lng": 121.0466558
      },
      {
        "lat": 14.5073737,
        "lng": 121.0465646
      },
      {
        "lat": 14.5077746,
        "lng": 121.0463548
      },
      {
        "lat": 14.5077826,
        "lng": 121.0463486
      },
      {
        "lat": 14.5078058,
        "lng": 121.0463306
      },
      {
        "lat": 14.5078236,
        "lng": 121.0463013
      },
      {
        "lat": 14.5034263,
        "lng": 121.0486191
      },
      {
        "lat": 14.5035456,
        "lng": 121.0486274
      },
      {
        "lat": 14.5036367,
        "lng": 121.0485991
      },
      {
        "lat": 14.5041367,
        "lng": 121.0483302
      }
    ],
    "color": "#FFFF00"
  },
  {
    "streetName": "Southeast Metro Manila Expressway",
    "coordinates": [
      {
        "lat": 14.5061425,
        "lng": 121.038229
      },
      {
        "lat": 14.5076019,
        "lng": 121.0410226
      },
      {
        "lat": 14.5098246,
        "lng": 121.0453884
      },
      {
        "lat": 14.5101648,
        "lng": 121.0458847
      },
      {
        "lat": 14.5106751,
        "lng": 121.0463353
      },
      {
        "lat": 14.5112606,
        "lng": 121.046582
      },
      {
        "lat": 14.5118838,
        "lng": 121.0467
      },
      {
        "lat": 14.5128011,
        "lng": 121.0467002
      },
      {
        "lat": 14.5132347,
        "lng": 121.0467625
      },
      {
        "lat": 14.513632,
        "lng": 121.0469408
      },
      {
        "lat": 14.5139773,
        "lng": 121.0472272
      },
      {
        "lat": 14.5142341,
        "lng": 121.0475695
      },
      {
        "lat": 14.5157973,
        "lng": 121.0506403
      },
      {
        "lat": 14.5160111,
        "lng": 121.050944
      },
      {
        "lat": 14.5162974,
        "lng": 121.0511787
      },
      {
        "lat": 14.5166194,
        "lng": 121.0513262
      },
      {
        "lat": 14.5169784,
        "lng": 121.0513739
      },
      {
        "lat": 14.5175921,
        "lng": 121.0513846
      },
      {
        "lat": 14.517904,
        "lng": 121.0513866
      },
      {
        "lat": 14.517991,
        "lng": 121.0513933
      },
      {
        "lat": 14.518054,
        "lng": 121.0514054
      },
      {
        "lat": 14.5181845,
        "lng": 121.051443
      },
      {
        "lat": 14.5182217,
        "lng": 121.0513237
      },
      {
        "lat": 14.5180814,
        "lng": 121.0512832
      },
      {
        "lat": 14.5180066,
        "lng": 121.0512689
      },
      {
        "lat": 14.5179089,
        "lng": 121.0512613
      },
      {
        "lat": 14.5169872,
        "lng": 121.0512488
      },
      {
        "lat": 14.5166554,
        "lng": 121.0512002
      },
      {
        "lat": 14.5163532,
        "lng": 121.0510661
      },
      {
        "lat": 14.5160981,
        "lng": 121.0508542
      },
      {
        "lat": 14.5159065,
        "lng": 121.0505799
      },
      {
        "lat": 14.5143165,
        "lng": 121.0474803
      },
      {
        "lat": 14.5140637,
        "lng": 121.047138
      },
      {
        "lat": 14.5137041,
        "lng": 121.0468376
      },
      {
        "lat": 14.5132678,
        "lng": 121.0466391
      },
      {
        "lat": 14.5128293,
        "lng": 121.0465758
      },
      {
        "lat": 14.5119072,
        "lng": 121.0465766
      },
      {
        "lat": 14.5113073,
        "lng": 121.0464587
      },
      {
        "lat": 14.5107452,
        "lng": 121.0462119
      },
      {
        "lat": 14.5102479,
        "lng": 121.0457881
      },
      {
        "lat": 14.5099207,
        "lng": 121.0452946
      },
      {
        "lat": 14.5077161,
        "lng": 121.0409742
      },
      {
        "lat": 14.5062465,
        "lng": 121.038166
      }
    ],
    "color": "#FFFF00"
  },
  {
    "streetName": "Accord Road",
    "coordinates": [
      {
        "lat": 14.5097021,
        "lng": 121.0471435
      },
      {
        "lat": 14.5087034,
        "lng": 121.047695
      },
      {
        "lat": 14.5097021,
        "lng": 121.0471435
      },
      {
        "lat": 14.5103463,
        "lng": 121.0467993
      }
    ],
    "color": "#FFFF00"
  },
  {
    "streetName": "Saint Luke Street",
    "coordinates": [
      {
        "lat": 14.5125032,
        "lng": 121.0507765
      },
      {
        "lat": 14.5126431,
        "lng": 121.0506739
      }
    ],
    "color": "#FFFF00"
  },
  {
    "streetName": "Anchor Street",
    "coordinates": [
      {
        "lat": 14.5104026,
        "lng": 121.0485066
      },
      {
        "lat": 14.5103596,
        "lng": 121.0484273
      },
      {
        "lat": 14.5100989,
        "lng": 121.0479351
      },
      {
        "lat": 14.5100584,
        "lng": 121.0478602
      },
      {
        "lat": 14.5100584,
        "lng": 121.0478602
      },
      {
        "lat": 14.5100247,
        "lng": 121.0477961
      },
      {
        "lat": 14.5100133,
        "lng": 121.0477723
      },
      {
        "lat": 14.5100133,
        "lng": 121.0477723
      },
      {
        "lat": 14.5097021,
        "lng": 121.0471435
      }
    ],
    "color": "#FFFF00"
  }
]
